faker_scifi/__init__.py
faker_scifi-0.1.1.dist-info/LICENSE
faker_scifi-0.1.1.dist-info/METADATA
faker_scifi-0.1.1.dist-info/WHEEL
faker_scifi-0.1.1.dist-info/top_level.txt
faker_scifi-0.1.1.dist-info/RECORD
